binn/__init__.py
binn/analysis/__init__.py
binn/analysis/explainer.py
binn/data/__init__.py
binn/data/downloads/mirbase_2_reactome_2025_01_16.txt
binn/data/downloads/reactome_pathways_names_2025_01_21.txt
binn/data/downloads/reactome_pathways_relation_2025_01_14.txt
binn/data/downloads/uniprot_2_reactome_2025_01_14.txt
binn/data/downloads/uniprotkb_human_2025_01_21.tsv
binn/model/__init__.py
binn/model/binn.py
binn/model/dataloader.py
binn/model/pathway_network.py
binn/model/trainer.py
binn/model/util.py
binn/plot/__init__.py
binn/plot/network.py
binn/plot/util.py
binn-0.1.1.dist-info/LICENSE
binn-0.1.1.dist-info/METADATA
binn-0.1.1.dist-info/WHEEL
binn-0.1.1.dist-info/top_level.txt
binn-0.1.1.dist-info/RECORD
