Metadata-Version: 2.1
Name: binn
Version: 0.1.1
Summary: A package to generate and interpret biologically informed neural networks.
Home-page: https://github.com/InfectionMedicineProteomics/BINN
Author: Erik Hartman
Author-email: Erik Hartman <erik.hartman@hotmail.com>, Aaron Scott <aaron.scott@med.lu.se>
License: MIT
Project-URL: Homepage, https://infectionmedicineproteomics.github.io/BINN/
Project-URL: Bug Tracker, https://github.com/InfectionMedicineProteomics/BINN/issues
Project-URL: Source, https://github.com/InfectionMedicineProteomics/BINN
Classifier: Programming Language :: Python :: 3
Classifier: License :: OSI Approved :: MIT License
Classifier: Operating System :: OS Independent
Requires-Python: >=3.9
License-File: LICENSE
Requires-Dist: numpy
Requires-Dist: networkx
Requires-Dist: pandas
Requires-Dist: torch
Requires-Dist: shap
Requires-Dist: matplotlib
